api/app/__init__.py
api/app/main.py
api/app/api/__init__.py
api/app/api/api_keys.py
api/app/api/auth.py
api/app/api/datasets.py
api/app/api/graders.py
api/app/api/permissions.py
api/app/api/scenarios.py
api/app/api/tasks.py
api/app/api/tenants.py
api/app/api/users.py
api/app/core/__init__.py
api/app/core/config.py
api/app/core/database.py
api/app/models/__init__.py
api/app/models/api_key.py
api/app/models/permission.py
api/app/models/task.py
api/app/models/tenant.py
api/app/models/user.py
api/app/schemas/__init__.py
api/app/schemas/api_key.py
api/app/schemas/permission.py
api/app/schemas/task.py
api/app/schemas/tenant.py
api/app/schemas/user.py
api/app/services/__init__.py
api/app/services/evaluation.py
api/app/services/storage.py
api/app/services/task_executor.py
api/app/utils/__init__.py
api/app/utils/deps.py
api/app/utils/permissions.py
api/app/utils/security.py
cookbooks/data_refinement/refinement.py
cookbooks/grader_validation/accuracy.py
cookbooks/grader_validation/grader_validator.py
cookbooks/grader_validation/rewardbench2.py
cookbooks/integrations/langsmith.py
cookbooks/pairwise_evaluation/pairwise_evaluation.py
cookbooks/training_judge_model/bradley-terry/dataset.py
cookbooks/training_judge_model/bradley-terry/trainer.py
cookbooks/training_judge_model/grpo/chat_rl_dataset.py
cookbooks/training_judge_model/grpo/pairwise/reward_fn.py
cookbooks/training_judge_model/grpo/pointwise/reward_fn.py
cookbooks/zero_shot_evaluation/__main__.py
cookbooks/zero_shot_evaluation/chart_generator.py
cookbooks/zero_shot_evaluation/query_generator.py
cookbooks/zero_shot_evaluation/report_generator.py
cookbooks/zero_shot_evaluation/response_collector.py
cookbooks/zero_shot_evaluation/schema.py
cookbooks/zero_shot_evaluation/zero_shot_pipeline.py
examples/scenario_evaluation_example.py
modelselect/__init__.py
modelselect/analyzer/__init__.py
modelselect/analyzer/base_analyzer.py
modelselect/analyzer/pairwise_analyzer.py
modelselect/analyzer/statistical/__init__.py
ms_modelselect-0.2.0.dist-info/licenses/LICENSE
ms_modelselect-0.2.0.dist-info/METADATA
ms_modelselect-0.2.0.dist-info/WHEEL
ms_modelselect-0.2.0.dist-info/top_level.txt
ms_modelselect-0.2.0.dist-info/RECORD
