Metadata-Version: 2.4
Name: ms-modelselect
Version: 0.2.0
Summary: ModelSelect: A Unified Framework for Holistic Evaluation and Quality Reward
Author-email: Qiao Cai <qiao.cai@alibaba-inc.com>, Haoran Chen <congling.chr@alibaba-inc.com>, Yuhao Cui <cyh262498@alibaba-inc.com>, Jiaji Deng <dengjiaji.djj@alibaba-inc.com>, Yiwen Ding <dingyiwen.dyw@antgroup.com>, Qingxu Fu <fuqingxu.fqx@alibaba-inc.com>, Yuan Gao <yunze.gy@alibaba-inc.com>, Sen Huang <huangsen.huang@alibaba-inc.com>, Weidan Kong <weidan.kong@alibaba-inc.com>, Li Yu <jinli.yl@alibaba-inc.com>, Boyin Liu <liuboyin.lby@alibaba-inc.com>, Zhaoyang Liu <jingmu.lzy@alibaba-inc.co
License-Expression: Apache-2.0
Project-URL: Homepage, https://github.com/agentscope-ai/ModelSelect
Project-URL: Repository, https://github.com/agentscope-ai/ModelSelect
Project-URL: Documentation, https://agentscope-ai.github.io/ModelSelect/
Keywords: deep-learning,evaluation,ai-model,llm
Classifier: Development Status :: 4 - Beta
Classifier: Programming Language :: Python :: 3
Classifier: Programming Language :: Python :: 3.10
Classifier: Programming Language :: Python :: 3.11
Classifier: Programming Language :: Python :: 3.12
Classifier: Operating System :: OS Independent
Classifier: Intended Audience :: Developers
Classifier: Intended Audience :: Science/Research
Classifier: Topic :: Scientific/Engineering :: Artificial Intelligence
Requires-Python: >=3.10
License-File: LICENSE
Requires-Dist: pandas<3.0.0,>=2.2.3
Requires-Dist: loguru<0.8.0,>=0.7.3
Requires-Dist: json_repair<1.0.0,>=0.54.0
Requires-Dist: pydantic<3.0.0,>=2.11.5
Requires-Dist: openai<2.0.0,>=1.92.0
Requires-Dist: tenacity<10.0.0,>=9.1.0
Requires-Dist: math-verify<0.8.0,>=0.7.0
Requires-Dist: tqdm<5.0.0,>=4.66.0
Requires-Dist: fire
Requires-Dist: numpy<2.0.0,>=1.22.0
Requires-Dist: dashscope>=1.19.0
Requires-Dist: tiktoken>=0.7.0
Requires-Dist: nltk>=3.8.1
Requires-Dist: jieba>=0.42.1
Requires-Dist: sacrebleu>=2.0.0
Requires-Dist: rouge-score>=0.1.2
Requires-Dist: python-Levenshtein>=0.20.0
Requires-Dist: scikit-learn>=1.0.0
Provides-Extra: dev
Requires-Dist: pre-commit; extra == "dev"
Requires-Dist: pytest<9.0.0,>=8.3.5; extra == "dev"
Requires-Dist: sphinx-gallery; extra == "dev"
Requires-Dist: furo; extra == "dev"
Requires-Dist: myst_parser; extra == "dev"
Requires-Dist: anyio; extra == "dev"
Requires-Dist: pytest-asyncio; extra == "dev"
Requires-Dist: pytest-tornasync; extra == "dev"
Requires-Dist: pytest-trio; extra == "dev"
Requires-Dist: pytest-twisted; extra == "dev"
Requires-Dist: twisted; extra == "dev"
Requires-Dist: python-dotenv; extra == "dev"
Requires-Dist: matplotlib<4.0.0,>=3.7.0; extra == "dev"
Provides-Extra: verl
Requires-Dist: transformers<5.0.0,>=4.52.4; extra == "verl"
Requires-Dist: verl; extra == "verl"
Provides-Extra: saas
Requires-Dist: fastapi<0.120.0,>=0.109.0; extra == "saas"
Requires-Dist: uvicorn[standard]<0.35.0,>=0.27.0; extra == "saas"
Requires-Dist: sqlalchemy<2.1.0,>=2.0.25; extra == "saas"
Requires-Dist: aiomysql<0.3.0,>=0.2.0; extra == "saas"
Requires-Dist: pymysql<1.2.0,>=1.1.0; extra == "saas"
Requires-Dist: alembic<2.0.0,>=1.13.0; extra == "saas"
Requires-Dist: email-validator<3.0.0,>=2.1.0; extra == "saas"
Requires-Dist: pydantic-settings<3.0.0,>=2.1.0; extra == "saas"
Requires-Dist: python-jose[cryptography]<4.0.0,>=3.3.0; extra == "saas"
Requires-Dist: passlib[bcrypt]<1.8.0,>=1.7.4; extra == "saas"
Requires-Dist: python-multipart<0.1.0,>=0.0.6; extra == "saas"
Requires-Dist: minio<8.0.0,>=7.2.0; extra == "saas"
Requires-Dist: redis<6.0.0,>=5.0.0; extra == "saas"
Requires-Dist: httpx<0.28.0,>=0.26.0; extra == "saas"
Requires-Dist: requests<3.0.0,>=2.31.0; extra == "saas"
Provides-Extra: all
Requires-Dist: ms-modelselect[dev,saas,verl]; extra == "all"
Dynamic: license-file
